Workbook

Sheet 1
C1: Данные для переноса в справку | D1: Сумма прописью
A2: Договор | B2: 1701-17887-2025 | C2: =+B2 -> 1701-17887-2025
A3: Дата договора | B3: 45765 | C3: =TEXT(B3,"[$-FC19]ДД ММММ ГГГГ")&" г." -> 18 апреля 2025 г.
A4: Фамилия | B4: Камилова | C4: =+B4 -> Камилова
A5: Имя | B5: Шахноза | C5: =+B5 -> Шахноза
A6: Отчетство | B6: Талыпжанқызы | C6: =+B6 -> Талыпжанқызы
A7: по состоянию на дату | B7: 46013 | C7: =TEXT(B7,"[$-FC19]ДД ММММ ГГГГ")&" г." -> 22 декабря 2025 г.
A8: Сумма задолженности | C8: =SUM(C9:C11) -> 7652278 | D8: один миллион пятьсот сорок шесть тысяч
A9: ОД | B9: 6551320 | C9: =+ROUNDUP(B9,0) -> 6551320 | D9: один миллион триста семьдесят тысяч четыреста шестьдесят пять
A10: % | B10: 799832 | C10: =+ROUNDUP(B10,0) -> 799832 | D10: сто сорок две тысячи двести пятнадцать
A11: штраф | B11: 301126 | C11: =+ROUNDUP(B11,0) -> 301126 | D11: тридцать три тысячи триста двадцать
A12: Госпошлина | B12: 295548 | C12: =+ROUNDUP(B12,0) -> 295548 | D12: Двести девяносто пять тысяч пятьсот сорок восемь
A13: Дата образования задолженности | C13: =TEXT(B13,"[$-FC19]ДД ММММ ГГГГ")&" г." -> 00 января 1900 г.
A14: Сумма займа | B14: 7000000 | C14: =+B14 -> 7000000
A15: Сумма ранее начисленной пени/штрафов | C15: =+B15 -> 0
A16: Максимальная сумма штрафа | B16: =B14*10% -> 700000
A17: Подписант Должность | B17: Аналитик
A18: Подписант ФИО | B18: Болат Е.А. | C18: 44972 | D18: =C18+17 -> 44989
A19: Расчет штрафа проверка | B19: Сумма задолженности по очередному платежу по графику | C19: дата начала просрочки | D19: Дата для расчета просрочки | E19: дней просрочки | F19: начислено | G19: оплачено | H19: к оплате
A20: 1 просроч.платеж | B20: 240864 | C20: =+B13 -> 0 | D20: =IF(C20>DATE(2020,6,15),C20,IF(C20>DATE(2020,3,14),DATE(2020,6,16),C20)) -> 0 | E20: =+IF(D20<=DATE(2020,3,15),DATE(2020,3,15)-D20+$B$7-DATE(2020,6,16),$B$7-D20) -> 45920 | F20: =+IF(E20>0,B20*0.5%*E20,0) -> 55302374 | H20: =F20-G20 -> 55302374
A21: 2 просроч.платеж | B21: 240864 | C21: =DATE(YEAR(B13),MONTH(B13)+1,DAY(B13)) -> 31 | D21: =IF(C21>DATE(2020,6,15),C21,IF(C21>DATE(2020,3,14),DATE(2020,6,16),C21)) -> 31 | E21: =+IF(D21<=DATE(2020,3,15),DATE(2020,3,15)-D21+$B$7-DATE(2020,6,16),$B$7-D21) -> 45889 | F21: =+IF(E21>0,B21*0.5%*E21,0) -> 55265040 | H21: =F21-G21 -> 55265040
A22: 3 просроч.платеж | B22: 240864 | C22: =DATE(YEAR(C21),MONTH(C21)+1,DAY(C21)) -> 62 | D22: =IF(C22>DATE(2020,6,15),C22,IF(C22>DATE(2020,3,14),DATE(2020,6,16),C22)) -> 62 | E22: =+IF(D22<=DATE(2020,3,15),DATE(2020,3,15)-D22+$B$7-DATE(2020,6,16),$B$7-D22) -> 45858 | F22: =+IF(E22>0,B22*0.5%*E22,0) -> 55227707 | H22: =F22-G22 -> 55227707
A23: 4 просроч.платеж | B23: 240864 | C23: =DATE(YEAR(C22),MONTH(C22)+1,DAY(C22)) -> 93 | D23: =IF(C23>DATE(2020,6,15),C23,IF(C23>DATE(2020,3,14),DATE(2020,6,16),C23)) -> 93 | E23: =+IF(D23<=DATE(2020,3,15),DATE(2020,3,15)-D23+$B$7-DATE(2020,6,16),$B$7-D23) -> 45827 | F23: =+IF(E23>0,B23*0.5%*E23,0) -> 55190373 | H23: =+F23-G23 -> 55190373
A24: 5 просроч.платеж | B24: 240864 | C24: =DATE(YEAR(C23),MONTH(C23)+1,DAY(C23)) -> 123 | D24: =IF(C24>DATE(2020,6,15),C24,IF(C24>DATE(2020,3,14),DATE(2020,6,16),C24)) -> 123 | E24: =+IF(D24<=DATE(2020,3,15),DATE(2020,3,15)-D24+$B$7-DATE(2020,6,16),$B$7-D24) -> 45797 | F24: =+IF(E24>0,B24*0.5%*E24,0) -> 55154243 | H24: =F24-G24 -> 55154243
A25: 6 просроч.платеж | B25: 240864 | C25: =DATE(YEAR(C24),MONTH(C24)+1,DAY(C24)) -> 154 | D25: =IF(C25>DATE(2020,6,15),C25,IF(C25>DATE(2020,3,14),DATE(2020,6,16),C25)) -> 154 | E25: =+IF(D25<=DATE(2020,3,15),DATE(2020,3,15)-D25+$B$7-DATE(2020,6,16),$B$7-D25) -> 45766 | F25: =+IF(E25>0,B25*0.5%*E25,0) -> 55116909 | H25: =F25-G25 -> 55116909
A26: 7 просроч.платеж | B26: 240864 | C26: =DATE(YEAR(C25),MONTH(C25)+1,DAY(C25)) -> 184 | D26: =IF(C26>DATE(2020,6,15),C26,IF(C26>DATE(2020,3,14),DATE(2020,6,16),C26)) -> 184 | E26: =+IF(D26<=DATE(2020,3,15),DATE(2020,3,15)-D26+$B$7-DATE(2020,6,16),$B$7-D26) -> 45736 | F26: =+IF(E26>0,B26*0.5%*E26,0) -> 55080780 | H26: =F26-G26 -> 55080780
A27: 8 просроч.платеж | B27: 0 | C27: =DATE(YEAR(C26),MONTH(C26)+1,DAY(C26)) -> 215 | D27: =IF(C27>DATE(2020,6,15),C27,IF(C27>DATE(2020,3,14),DATE(2020,6,16),C27)) -> 215 | E27: =+IF(D27<=DATE(2020,3,15),DATE(2020,3,15)-D27+$B$7-DATE(2020,6,16),$B$7-D27) -> 45705 | F27: =+IF(E27>0,B27*0.5%*E27,0) -> 0 | H27: =F27-G27 -> 0
A28: 9 просроч.платеж | B28: 0 | C28: =DATE(YEAR(C27),MONTH(C27)+1,DAY(C27)) -> 246 | D28: =IF(C28>DATE(2020,6,15),C28,IF(C28>DATE(2020,3,14),DATE(2020,6,16),C28)) -> 246 | E28: =+IF(D28<=DATE(2020,3,15),DATE(2020,3,15)-D28+$B$7-DATE(2020,6,16),$B$7-D28) -> 45674 | F28: =+IF(E28>0,B28*0.5%*E28,0) -> 0 | H28: =F28-G28 -> 0
A29: 10 просроч.платеж | B29: =+B28 -> 0 | C29: =DATE(YEAR(C28),MONTH(C28)+1,DAY(C28)) -> 276 | D29: =IF(C29>DATE(2020,6,15),C29,IF(C29>DATE(2020,3,14),DATE(2020,6,16),C29)) -> 276 | E29: =+IF(D29<=DATE(2020,3,15),DATE(2020,3,15)-D29+$B$7-DATE(2020,6,16),$B$7-D29) -> 45644 | F29: =+IF(E29>0,B29*0.5%*E29,0) -> 0 | H29: =F29-G29 -> 0
A30: 11 просроч.платеж | B30: =+B29 -> 0 | C30: =DATE(YEAR(C29),MONTH(C29)+1,DAY(C29)) -> 307 | D30: =IF(C30>DATE(2020,6,15),C30,IF(C30>DATE(2020,3,14),DATE(2020,6,16),C30)) -> 307 | E30: =+IF(D30<=DATE(2020,3,15),DATE(2020,3,15)-D30+$B$7-DATE(2020,6,16),$B$7-D30) -> 45613 | F30: =+IF(E30>0,B30*0.5%*E30,0) -> 0 | H30: =F30-G30 -> 0
A31: 12 просроч.платеж | B31: =+B30 -> 0 | C31: =DATE(YEAR(C30),MONTH(C30)+1,DAY(C30)) -> 337 | D31: =IF(C31>DATE(2020,6,15),C31,IF(C31>DATE(2020,3,14),DATE(2020,6,16),C31)) -> 337 | E31: =+IF(D31<=DATE(2020,3,15),DATE(2020,3,15)-D31+$B$7-DATE(2020,6,16),$B$7-D31) -> 45583 | F31: =+IF(E31>0,B31*0.5%*E31,0) -> 0 | H31: =F31-G31 -> 0
D36: 45133 | E36: 44928
D37: 45015 | E37: 45160
D38: =E37-D36 -> 27 | E38: =E37-E36 -> 232
C40: 44989 | D40: =E37-C40 -> 171
C43: 45027
C44: =C43+13 -> 45040

Sheet штраф более 10% и ранее начисл
A2: Расчет ссудной задолженности
A4: =CONCATENATE("По договору займа №",'1'!C2," от ",'1'!C3,", заключенному с ",'1'!C4," ",'1'!C5," ",'1'!C6,", по состоянию на ",'1'!C7," ссудная задолженность составляет ",TEXT('1'!C8,"### ### ###")," (",'1'!D8,") тенге, из них") -> По договору займа №1701-17887-2025 от 18 апреля 2025 г., заключенному с Камилова Шахноза Талыпжанқызы, по состоянию на 22 декабря 2025 г. ссудная задолженность составляет 7 652 278 (один миллион пятьсот сорок шесть тысяч) тенге, из них
A5: Ø | B5: =CONCATENATE("Основной долг - ",TEXT('1'!C9,"### ### ###")," (",'1'!D9,") тенге;") -> Основной долг - 6 551 320 (один миллион триста семьдесят тысяч четыреста шестьдесят пять) тенге;
A6: Ø | B6: =CONCATENATE("Вознаграждение – ",TEXT('1'!C10,"### ### ###")," (",'1'!D10,") тенге;") -> Вознаграждение – 799 832 (сто сорок две тысячи двести пятнадцать) тенге;
A7: Ø | B7: =CONCATENATE("Госпошлина – ",TEXT('1'!C12,"### ### ###")," (",'1'!D12,") тенге;") -> Госпошлина – 295 548 (Двести девяносто пять тысяч пятьсот сорок восемь) тенге;
A8: Ø | B8: =CONCATENATE("Неустойка (штраф за несвоевременное погашение) – ",TEXT('1'!C11,"### ### ###")," (",'1'!D11,") тенге, из них:") -> Неустойка (штраф за несвоевременное погашение) – 301 126 (тридцать три тысячи триста двадцать) тенге, из них:
B10: РАСЧЕТ НЕУСТОЙКИ ЗА НЕСВОЕВРЕМЕННУЮ УПЛАТУ ПРОЦЕНТОВ
B11: Период для расчета | C11: Сумма просроченных процентов, тенге | D11: Ставка неустойки в день (%) | E11: Количество дней в периоде | F11: Сумма неустойки, тенге | G11: Формула расчета
B12: 09.04.2025 - 15.04.2025 | C12: 26856 | D12: 0.5 | E12: 7 | F12: 939.96 | G12: 26 856 * 0.5% * 7
B13: 27.04.2025 - 20.05.2025 | C13: 53491 | D13: 0.5 | E13: 24 | F13: 6418.92 | G13: 53 491 * 0.5% * 24
B14: 21.05.2025 - 25.06.2025 | C14: 37933 | D14: 0.5 | E14: 36 | F14: 6827.94 | G14: 37 933 * 0.5% * 36
B15: 27.05.2025 - 25.06.2025 | C15: 54995 | D15: 0.5 | E15: 30 | F15: 8249.25 | G15: 54 995 * 0.5% * 30
B17: РАСЧЕТ НЕУСТОЙКИ ЗА НЕСВОЕВРЕМЕННУЮ УПЛАТУ ОСНОВНОГО ДОЛГА
B18: Период для расчета | C18: Сумма просроченных процентов, тенге | D18: Ставка неустойки в день (%) | E18: Количество дней в периоде | F18: Сумма неустойки, тенге | G18: Формула расчета
B19: 27.04.2025 - 20.05.2025 | C19: 45442 | D19: 0.5 | E19: 24 | F19: 5453.04 | G19: 45 442 * 0.5% * 24
B20: 27.05.2025 - 25.06.2025 | C20: 47146 | D20: 0.5 | E20: 30 | F20: 7071.9 | G20: 47 146 * 0.5% * 30
B21: Операционный менеджер Койбасова Е.Б.

Sheet Лист2
A1: РЕЕСТР
A2: платежей, поступивших на текущий счет, открытый в АО "Народный банк Казахстана"
A3: по договору № | C3: 0202-13612-2024
A5: Дата, время | B5: № Транзакции | C5: ИИН | D5: Сумма | E5: Договор
A6: 27.02.2024 00:00:00 | B6: 405894574441 | C6: 910910301382 | D6: 103000 | E6: 0202-13612-2024
A7: 24.03.2024 01:00:00 | B7: 408494619220 | C7: 910910301382 | D7: 103000 | E7: 0202-13612-2024
A8: 24.04.2024 01:00:00 | B8: 411594396755 | C8: 910910301382 | D8: 104000 | E8: 0202-13612-2024
A9: 23.05.2024 01:00:00 | B9: 414494723828 | C9: 910910301382 | D9: 103500 | E9: 0202-13612-2024
A10: 25.06.2024 01:00:00 | B10: 417794320918 | C10: 910910301382 | D10: 105000 | E10: 0202-13612-2024
A11: 24.07.2024 01:00:00 | B11: 420694948120 | C11: 910910301382 | D11: 103000 | E11: 0202-13612-2024
A12: 27.08.2024 01:00:00 | B12: 424094471808 | C12: 910910301382 | D12: 105000 | E12: 0202-13612-2024
A13: 24.09.2024 01:00:00 | B13: 426894547594 | C13: 910910301382 | D13: 105000 | E13: 0202-13612-2024
A14: 28.10.2024 01:00:00 | B14: 430294925199 | C14: 910910301382 | D14: 105000 | E14: 0202-13612-2024
A15: 25.11.2024 01:00:00 | B15: 433094781113 | C15: 910910301382 | D15: 105000 | E15: 0202-13612-2024
A16: 17.12.2024 01:00:00 | B16: 435294613037 | C16: 910910301382 | D16: 105500 | E16: 0202-13612-2024
A17: 31.01.2025 02:00:00 | B17: 503194221567 | C17: 910910301382 | D17: 105000 | E17: 0202-13612-2024
... A22: 27.06.2025 02:00:00 | B22: 517894617395 | C22: 910910301382 | D22: 100000 | E22: 0202-13612-2024
A23: ИТОГО поступлений | D23: =SUM(D6:D22) -> 1604000
A24: РЕЕСТР
A25: платежей, поступивших на текущий счет, открытый в АО "Банк ЦентрКредит"
A26: по договору №
A28: Дата, время | B28: № Транзакции | C28: ИИН | D28: Сумма | E28: Договор
A38: ИТОГО поступлений | D38: =SUM(D29:D37) -> 0
A39: РЕЕСТР
A40: платежей, поступивших в кассу ТОО "МФО "Swiss Capital (Свисс Капитал)"
A41: по договору №
A43: Дата, время | B43: № Транзакции | C43: ИИН | D43: Сумма | E43: Договор
A51: ИТОГО поступлений | D51: =SUM(D44:D50) -> 0
A53: РЕЕСТР
A54: платежей, поступивших посредством платежной системы Homebank
A55: по договору №
A57: Дата, время | B57: № Транзакции | C57: ИИН | D57: Сумма | E57: Договор
A65: ИТОГО поступлений | D65: =SUM(D58:D64) -> 0
A67: ВСЕГО поступлений по всем платежным системам | E67: =D65+D51+D38+D23 -> 1604000
A69: Операционный менеджер
A70: ТОО "МФО "Swiss Capital (Свисс Капитал)" | D70: Койбасова Е.Б.

Sheet Лист1
A1: Дата | B1: Тип ДДС | C1: Сумма | D1: Банк/Касса | E1: Номер ордера
A2: 24.01.2024 17:19:40 | B2: Расход | C2: 2000000 | D2: Б АО «Kaspi Bank» -> KZ70722S000004228073 | E2: 2154
A3: 27.02.2024 00:00:00 | B3: П | C3: 103000 | D3: Б АО "Народный Банк Казахстана" -> Homebank | E3: 405894574441
A4: 24.03.2024 01:00:00 | B4: П | C4: 103000 | D4: Б АО "Народный Банк Казахстана" -> Homebank | E4: 408494619220
A5: 24.04.2024 01:00:00 | B5: П | C5: 104000 | D5: Б АО "Народный Банк Казахстана" -> Homebank | E5: 411594396755
A6: 23.05.2024 01:00:00 | B6: П | C6: 103500 | D6: Б АО "Народный Банк Казахстана" -> Homebank | E6: 414494723828
A7: 25.06.2024 01:00:00 | B7: П | C7: 105000 | D7: Б АО "Народный Банк Казахстана" -> Homebank | E7: 417794320918
A8: 24.07.2024 01:00:00 | B8: П | C8: 103000 | D8: Б АО "Народный Банк Казахстана" -> Homebank | E8: 420694948120
A9: 27.08.2024 01:00:00 | B9: П | C9: 105000 | D9: Б АО "Народный Банк Казахстана" -> Homebank | E9: 424094471808
A10: 24.09.2024 01:00:00 | B10: П | C10: 105000 | D10: Б АО "Народный Банк Казахстана" -> Homebank | E10: 426894547594
A11: 28.10.2024 01:00:00 | B11: П | C11: 105000 | D11: Б АО "Народный Банк Казахстана" -> Homebank | E11: 430294925199
A12: 25.11.2024 01:00:00 | B12: П | C12: 105000 | D12: Б АО "Народный Банк Казахстана" -> Homebank | E12: 433094781113
A13: 17.12.2024 01:00:00 | B13: П | C13: 105500 | D13: Б АО "Народный Банк Казахстана" -> Homebank | E13: 435294613037
... A19: 27.06.2025 02:00:00 | B19: П | C19: 100000 | D19: Б АО "Народный Банк Казахстана" -> Homebank | E19: 517894617395

Sheet реестр платежки
A1: РЕЕСТР
A2: платежей, поступивших на текущий счет, открытый в АО "Народный банк Казахстана"
A3: по договору №
A5: Дата, время | B5: № Транзакции | C5: ИИН | D5: Сумма | E5: Договор
A10: ИТОГО поступлений | D10: =SUM(D6:D9) -> 0
A11: РЕЕСТР
A12: платежей, поступивших на текущий счет, открытый в АО "Банк ЦентрКредит"
A13: по договору №
A15: Дата, время | B15: № Транзакции | C15: ИИН | D15: Сумма | E15: Договор
A21: ИТОГО поступлений | D21: =SUM(D16:D20) -> 0
A22: РЕЕСТР
A23: платежей, поступивших в кассу ТОО "МФО "Swiss Capital (Свисс Капитал)"
A24: по договору №
A26: Дата, время | B26: № Транзакции | C26: ИИН | D26: Сумма | E26: Договор
A34: ИТОГО поступлений | D34: =SUM(D27:D33) -> 0
A36: РЕЕСТР
A37: платежей, поступивших посредством платежной системы Homebank
A38: по договору №
A40: Дата, время | B40: № Транзакции | C40: ИИН | D40: Сумма | E40: Договор
A43: ИТОГО поступлений | D43: =SUM(D41:D42) -> 0
A45: ВСЕГО поступлений по всем платежным системам | E45: =D43+D34+D21+D10 -> 0
A47: Аналитик
A48: ТОО "МФО "Swiss Capital (Свисс Капитал)" | D48: Болат Е.А.
